configura.py
paress.py
plataforma.py
reconex.py
paress/__init__.py
paress/configura.py
paress/paress.py
paress/plataforma.py
paress/reconex.py
paress - copia/__init__.py
paress - copia/compatibilidad.py
paress - copia/configura.py
paress - copia/paress.py
paress - copia/plataforma.py
paress - copia/reconex.py
paress-0.0.400.dist-info/LICENSE
paress-0.0.400.dist-info/METADATA
paress-0.0.400.dist-info/WHEEL
paress-0.0.400.dist-info/top_level.txt
paress-0.0.400.dist-info/RECORD
