Metadata-Version: 2.1
Name: paress
Version: 0.0.400
Summary: Utilidad para Web Scrapping en el Portal de Archivos Españoles-PARES
Home-page: https://github.com/jairomelo/PARESS
Author: Jairo Antonio Melo Flórez
Author-email: jairom@colmich.edu.mx
License: UNKNOWN
Platform: UNKNOWN
Classifier: Programming Language :: Python :: 3.8
Classifier: License :: OSI Approved :: MIT License
Classifier: Operating System :: OS Independent
Requires-Dist: selenium
Requires-Dist: beautifulsoup4
Requires-Dist: requests
Requires-Dist: chromedriver-autoinstaller
